{
  "apps": {
    "notepad": {
      "target": "C:/Windows/System32/notepad.exe",
      "enabled": true,
      "aliases": ["notepad", "note pad"]
    },
    "chrome": {
      "target": "C:/Program Files/Google/Chrome/Application/chrome.exe",
      "enabled": true,
      "aliases": ["chrome", "google chrome", "browser"]
    }
  },
  "sites": {
    "youtube": {
      "target": "https://youtube.com",
      "enabled": true,
      "aliases": [
        "yt",
        "youtube",
        "you tube",
        "u tube",
        "utube",
        "you toob",
        "you two",
        "you too",
        "you to"
      ]
    },
    "google": {
      "target": "https://google.com",
      "enabled": true,
      "aliases": ["google", "search", "google search"]
    }
  }
}
